e2b/__init__.py
e2b/api/__init__.py
e2b/api/client/__init__.py
e2b/api/client/api/__init__.py
e2b/api/client/api/sandboxes/__init__.py
e2b/api/client/api/sandboxes/delete_sandboxes_sandbox_id.py
e2b/api/client/api/sandboxes/get_sandboxes.py
e2b/api/client/api/sandboxes/get_sandboxes_metrics.py
e2b/api/client/api/sandboxes/get_sandboxes_sandbox_id.py
e2b/api/client/api/sandboxes/get_sandboxes_sandbox_id_logs.py
e2b/api/client/api/sandboxes/get_sandboxes_sandbox_id_metrics.py
e2b/api/client/api/sandboxes/get_v2_sandboxes.py
e2b/api/client/api/sandboxes/post_sandboxes.py
e2b/api/client/api/sandboxes/post_sandboxes_sandbox_id_connect.py
e2b/api/client/api/sandboxes/post_sandboxes_sandbox_id_pause.py
e2b/api/client/api/sandboxes/post_sandboxes_sandbox_id_refreshes.py
e2b/api/client/api/sandboxes/post_sandboxes_sandbox_id_resume.py
e2b/api/client/api/sandboxes/post_sandboxes_sandbox_id_timeout.py
e2b/api/client/api/templates/__init__.py
e2b/api/client/api/templates/delete_templates_template_id.py
e2b/api/client/api/templates/get_templates.py
e2b/api/client/api/templates/get_templates_template_id.py
e2b/api/client/api/templates/get_templates_template_id_builds_build_id_status.py
e2b/api/client/api/templates/get_templates_template_id_files_hash.py
e2b/api/client/api/templates/patch_templates_template_id.py
e2b/api/client/api/templates/post_templates.py
e2b/api/client/api/templates/post_templates_template_id.py
e2b/api/client/api/templates/post_templates_template_id_builds_build_id.py
e2b/api/client/api/templates/post_v2_templates.py
e2b/api/client/api/templates/post_v3_templates.py
e2b/api/client/api/templates/post_v_2_templates_template_id_builds_build_id.py
e2b/api/client/client.py
e2b/api/client/errors.py
e2b/api/client/models/__init__.py
e2b/api/client/models/aws_registry.py
e2b/api/client/models/aws_registry_type.py
e2b/api/client/models/build_log_entry.py
e2b/api/client/models/build_status_reason.py
e2b/api/client/models/connect_sandbox.py
cmsbx-0.0.6.dist-info/LICENSE
cmsbx-0.0.6.dist-info/METADATA
cmsbx-0.0.6.dist-info/WHEEL
cmsbx-0.0.6.dist-info/RECORD
